venv_stack/__init__.py
venv_stack/__main__.py
venv_stack/manager.py
venv_stack/shells.py
venv_stack-1.0.0.dist-info/METADATA
venv_stack-1.0.0.dist-info/WHEEL
venv_stack-1.0.0.dist-info/entry_points.txt
venv_stack-1.0.0.dist-info/top_level.txt
venv_stack-1.0.0.dist-info/RECORD
