Metadata-Version: 2.4
Name: venv_stack
Version: 1.0.0
Summary: A layered virtual environment manager compatible with PEP 668
Author-email: Ata Hakçıl <ignis@ignis.wtf>
License: MIT
Project-URL: Homepage, https://github.com/ignis-sec/venv-stack
Project-URL: Repository, https://github.com/ignis-sec/venv-stack
Project-URL: Issues, https://github.com/ignis-sec/venv-stack/issues
Keywords: virtualenv,venv,python,PEP 668,environment management
Requires-Python: >=3.7
Dynamic: requires-python
